Lavoisier/__init__.py
Lavoisier/additional_files.py
Lavoisier/collection.py
Lavoisier/conversion.py
Lavoisier/conversion_caller.py
Lavoisier/mapping.py
Lavoisier/units.py
Lavoisier/Mapping_files/ISIC.txt
Lavoisier/Mapping_files/Id_elementary_exchanges.csv
Lavoisier/Mapping_files/classification.xml
Lavoisier/Mapping_files/compartment_w.csv
Lavoisier/Mapping_files/flowCategories.xml
Lavoisier/Mapping_files/locations.xml
Lavoisier/__pycache__/__init__.cpython-38.pyc
Lavoisier/__pycache__/conversion_caller.cpython-38.pyc
Lavoisier-2.0.14.dist-info/LICENSE
Lavoisier-2.0.14.dist-info/METADATA
Lavoisier-2.0.14.dist-info/WHEEL
Lavoisier-2.0.14.dist-info/top_level.txt
Lavoisier-2.0.14.dist-info/RECORD
