Metadata-Version: 2.1
Name: Lavoisier
Version: 2.0.14
Summary: This package converts Life Cycle Assessment format Ecospold2 (ecoinvent format) to ILCD (jrc format). Files can be converted by file using the 'convert_file_to_ILCD' function or entire directory using the 'convert_dir_to_ILCD' function. Lavoisier is developed by the Center of Life Cycle Sustainable Assessment (Gyro) of the Federal University of Technology - Paraná (UTFPR) and the  Brazilian Institute for Information in Science and Technology (IBICT)
Home-page: https://github.com/JosePauloSavioli/IBICT-converter
Author: José Paulo Pereira das Dores Savioli
Author-email: jsavioli@alunos.utfpr.edu.br
License: UNKNOWN
Project-URL: Bug Tracker, https://github.com/JosePauloSavioli/IBICT-converter/issues
Platform: UNKNOWN
Classifier: Programming Language :: Python :: 3.8
Classifier: Programming Language :: Python :: 3.9
Classifier: License :: OSI Approved :: GNU General Public License v3 (GPLv3)
Classifier: Operating System :: OS Independent
Requires-Python: >=3.8
License-File: LICENSE
Requires-Dist: lxml
Requires-Dist: importlib-metadata
